vpm/__init__.py
vpm/__main__.py
vpm/cli.py
vpm/db.py
vpm/elements.py
vpm/home.py
vpm/parts.py
vpm/room.py
vpm/tasks.py
vpm/config/__init__.py
vpm/config/settings.py
vpm/database/__init__.py
vpm/database/config.py
vpm/database/engine.py
vpm/database/init.py
vpm/database/triggers.py
vpm/models/__init__.py
vpm/models/base.py
vpm/models/contacts.py
vpm/models/documents.py
vpm/models/elements.py
vpm/models/parts.py
vpm/models/picklist.py
vpm/models/property.py
vpm/models/tasks.py
vpm/services/base.py
vpm/services/database.py
vpm/services/elements.py
vpm/services/parts.py
vpm/services/property.py
vpm/utils/helpers.py
vpm_cli-0.1.1.dist-info/licenses/LICENSE
vpm_cli-0.1.1.dist-info/METADATA
vpm_cli-0.1.1.dist-info/WHEEL
vpm_cli-0.1.1.dist-info/entry_points.txt
vpm_cli-0.1.1.dist-info/top_level.txt
vpm_cli-0.1.1.dist-info/RECORD
