Metadata-Version: 2.4
Name: vpm-cli
Version: 0.1.1
Summary: VPM is a lightweight opensource home management system
Author-email: John Michael Lasalle <jml@jmlasalle.com>
License: MIT License
Project-URL: Homepage, https://github.com/jmlasalle/vpm
Project-URL: Repository, https://github.com/jmlasalle/vpm.git
Project-URL: Issues, https://github.com/jmlasalle/vpm/issues
Classifier: Development Status :: 2 - Pre-Alpha
Classifier: Intended Audience :: End Users/Desktop
Classifier: License :: OSI Approved :: MIT License
Classifier: Programming Language :: Python :: 3
Classifier: Programming Language :: Python :: 3.8
Classifier: Programming Language :: Python :: 3.9
Classifier: Programming Language :: Python :: 3.10
Classifier: Programming Language :: Python :: 3.11
Requires-Python: >=3.8
License-File: LICENSE
Requires-Dist: email_validator>=2.2.0
Requires-Dist: typer>=0.9.0
Requires-Dist: sqlmodel>=0.0.8
Requires-Dist: python-dateutil>=2.8.2
Requires-Dist: rich>=13.0.0
Requires-Dist: typing-extensions>=4.5.0
Requires-Dist: pydantic>=2.0.0
Requires-Dist: sqlalchemy>=2.0.0
Dynamic: license-file
